threader/__init__.py
threader/thread.py
threader-0.1.1.dist-info/LICENSE
threader-0.1.1.dist-info/WHEEL
threader-0.1.1.dist-info/METADATA
threader-0.1.1.dist-info/RECORD
