Metadata-Version: 1.2
Name: threader
Version: 0.1.1
Summary: Tools to quickly create twitter threads.
Home-page: https://github.com/choldgraf/threader
License: UNKNOWN
Author: Chris Holdgraf
Author-email: choldgraf@berkeley.edu
Classifier: License :: OSI Approved :: MIT License
